fsm.v

module fsm (
    input wire clk,
    input wire rst,
    input wire parity_en,
    input wire valid_in,
    output reg load_en,
    output reg shift_en,
    output reg busy,
    output reg [1:0] sel
);

    reg [2:0] current_state, next_state;
    reg [2:0] count;

    localparam S0     = 3'b000,
               START  = 3'b001,
               DATA   = 3'b010,
               PARITY = 3'b011,
               STOP   = 3'b100;

    always @(negedge clk or negedge rst) begin
        if (!rst) begin
            current_state <= S0;
            count         <= 3'b000;
        end else begin
            current_state <= next_state;
            if (current_state == DATA)
                count <= count + 1'b1;
            else
                count <= 3'b000;
        end
    end

    always @(*) begin
        load_en    = 1'b0;
        shift_en   = 1'b0;
        busy       = 1'b1;
        sel        = 2'b11;
        next_state = current_state;

        case (current_state)
            S0: begin 
                busy = 1'b0;
                if (valid_in) begin 
                    load_en    = 1'b1;
                    next_state = START;
                end else begin
                    next_state = S0;
                end
            end

            START: begin 
                sel        = 2'b00;
                next_state = DATA;
            end

            DATA: begin 
                sel      = 2'b01;
                shift_en = 1'b1;
                if (count != 3'd7) begin
                    next_state = DATA;
                end else begin
                    if (parity_en)
                        next_state = PARITY;
                    else
                        next_state = STOP;
                end
            end

            PARITY: begin 
                sel        = 2'b10;
                next_state = STOP;
            end

            STOP: begin 
                sel        = 2'b11;
                next_state = S0;
            end

            default: next_state = S0;
        endcase
    end

endmodule

mux.v
module mux(
    input wire data,
    input wire parity_out,
    input wire [1:0] sel,
    output reg  tx_out
);
always @(*) begin 
case(sel)  
2'b00: begin 
tx_out = 1'b0;
end
2'b01: begin 
tx_out = data;
end
2'b10: begin 
tx_out = parity_out;
end
2'b11: begin 
tx_out =1'b1;
end
default : tx_out =1'b1;



endcase
end
endmodule

parity.v

module parity (
    input  wire       parity_en,
    input  wire       parity_bit,
    input  wire [7:0] data,
    output reg        parity_out
);

    always @(*) begin 
        if (parity_en) begin
            if (!parity_bit) begin
                if (^data == 1'b1) 
                    parity_out = 1'b1;
                else 
                    parity_out = 1'b0;
            end else begin
                if (^data == 1'b0) 
                    parity_out = 1'b1;
                else 
                    parity_out = 1'b0;
            end
        end else begin
            parity_out = 1'b0;
        end
    end

endmodule

serializer.v
module serializer (
    input  wire       clk,
    input  wire       rst,
    input  wire       load_en,
    input  wire       shift_en,
    input  wire [7:0] data,
    output wire       ser_data
);

    reg [7:0] shift_reg;

    always @(posedge clk or posedge rst) begin
        if (rst) begin
            shift_reg <= 8'b0;
        end else if (load_en) begin
            shift_reg <= data;
        end else if (shift_en) begin
            shift_reg <= shift_reg >> 1;
        end
    end

    assign ser_data = shift_reg[0];

endmodule

uart.v

module uart_tx_top (
    input  wire       clk,
    input  wire       rst,
    input  wire       parity_bit,
    input  wire       parity_en,
    input  wire       valid_in,
    input  wire [7:0] p_data,
    output wire       tx_out,
    output wire       busy
);

    wire       ser_data_internal;
    wire       parity_out_internal;
    wire       load_en_internal;
    wire       shift_en_internal;
    wire [1:0] sel_internal;

    serializer A_serializer (
        .clk      (clk),                
        .rst      (rst),               
        .data     (p_data),             
        .load_en  (load_en_internal),   
        .shift_en (shift_en_internal),  
        .ser_data (ser_data_internal)   
    );

    parity A_parity (
        .parity_en  (parity_en),
        .parity_bit (parity_bit),
        .data       (p_data),
        .parity_out (parity_out_internal)
    );

    mux A_mux (
        .data       (ser_data_internal),
        .parity_out (parity_out_internal),
        .sel        (sel_internal),
        .tx_out     (tx_out)
    );

    fsm A_fsm (
        .clk        (clk),
        .rst        (rst),
        .parity_en  (parity_en),
        .valid_in   (valid_in),
        .load_en    (load_en_internal),
        .shift_en   (shift_en_internal),
        .busy       (busy),
        .sel        (sel_internal)
    );

endmodule

uart_tb.v
`timescale 1ns/1ps

module uart_tx_tb;

    reg        clk;
    reg        rst;
    reg        parity_bit;
    reg        parity_en;
    reg        valid_in;
    reg  [7:0] p_data;

    wire       tx_out;
    wire       busy;

    uart_tx_top uut (
        .clk        (clk),
        .rst        (rst),
        .parity_bit (parity_bit),
        .parity_en  (parity_en),
        .valid_in   (valid_in),
        .p_data     (p_data),
        .tx_out     (tx_out),
        .busy       (busy)
    );

    always #5 clk = ~clk;

    initial begin
        $dumpfile("uart_tx.vcd");
        $dumpvars(0, uart_tx_tb);

        clk        = 0;
        rst        = 0;
        parity_bit = 0;
        parity_en  = 0;
        valid_in   = 0;
        p_data     = 8'h00;

        #20;
        rst = 1;
        #20;

        p_data     = 8'b10100101; 
        parity_en  = 1'b1;
        parity_bit = 1'b0;
        valid_in   = 1'b1;
        #10;
        valid_in   = 1'b0;

        wait (busy == 1'b1);
        wait (busy == 1'b0);
        #20;

        p_data     = 8'b00111100; 
        parity_en  = 1'b1;
        parity_bit = 1'b1;
        valid_in   = 1'b1;
        #10;
        valid_in   = 1'b0;

        wait (busy == 1'b1);
        wait (busy == 1'b0);
        #20;

        p_data     = 8'b11111111; 
        parity_en  = 1'b0;
        valid_in   = 1'b1;
        #10;
        valid_in   = 1'b0;

        wait (busy == 1'b1);
        wait (busy == 1'b0);
        #20;

        p_data     = 8'b01010101;
        parity_en  = 1'b1;
        parity_bit = 1'b0;
        valid_in   = 1'b1;
        #10;
        valid_in   = 1'b0;

        wait (busy == 1'b1);
        wait (busy == 1'b0);
        
        p_data     = 8'b11001100;
        valid_in   = 1'b1;
        #10;
        valid_in   = 1'b0;

        wait (busy == 1'b1);
        wait (busy == 1'b0);
        #50;

        $stop;
    end

endmodule

uart_tx.vcd
$date
	Fri Aug 28 22:56:43 2026
$end
$version
	ModelSim Version 10.5b
$end
$timescale
	1ps
$end

$scope module uart_tx_tb $end
$var reg 1 ! clk $end
$var reg 1 " rst $end
$var reg 1 # parity_bit $end
$var reg 1 $ parity_en $end
$var reg 1 % valid_in $end
$var reg 8 & p_data [7:0] $end
$var wire 1 ' tx_out $end
$var wire 1 ( busy $end

$scope module uut $end
$var wire 1 ) clk $end
$var wire 1 * rst $end
$var wire 1 + parity_bit $end
$var wire 1 , parity_en $end
$var wire 1 - valid_in $end
$var wire 1 . p_data [7] $end
$var wire 1 / p_data [6] $end
$var wire 1 0 p_data [5] $end
$var wire 1 1 p_data [4] $end
$var wire 1 2 p_data [3] $end
$var wire 1 3 p_data [2] $end
$var wire 1 4 p_data [1] $end
$var wire 1 5 p_data [0] $end
$var wire 1 ' tx_out $end
$var wire 1 ( busy $end
$var wire 1 6 ser_data_internal $end
$var wire 1 7 parity_out_internal $end
$var wire 1 8 load_en_internal $end
$var wire 1 9 shift_en_internal $end
$var wire 1 : sel_internal [1] $end
$var wire 1 ; sel_internal [0] $end

$scope module A_serializer $end
$var wire 1 ) clk $end
$var wire 1 * rst $end
$var wire 1 8 load_en $end
$var wire 1 9 shift_en $end
$var wire 1 . data [7] $end
$var wire 1 / data [6] $end
$var wire 1 0 data [5] $end
$var wire 1 1 data [4] $end
$var wire 1 2 data [3] $end
$var wire 1 3 data [2] $end
$var wire 1 4 data [1] $end
$var wire 1 5 data [0] $end
$var wire 1 6 ser_data $end
$var reg 8 < shift_reg [7:0] $end
$upscope $end

$scope module A_parity $end
$var wire 1 , parity_en $end
$var wire 1 + parity_bit $end
$var wire 1 . data [7] $end
$var wire 1 / data [6] $end
$var wire 1 0 data [5] $end
$var wire 1 1 data [4] $end
$var wire 1 2 data [3] $end
$var wire 1 3 data [2] $end
$var wire 1 4 data [1] $end
$var wire 1 5 data [0] $end
$var reg 1 = parity_out $end
$upscope $end

$scope module A_mux $end
$var wire 1 6 data $end
$var wire 1 7 parity_out $end
$var wire 1 : sel [1] $end
$var wire 1 ; sel [0] $end
$var reg 1 > tx_out $end
$upscope $end

$scope module A_fsm $end
$var parameter 3 ? S0 $end
$var parameter 3 @ START $end
$var parameter 3 A DATA $end
$var parameter 3 B PARITY $end
$var parameter 3 C STOP $end
$var wire 1 ) clk $end
$var wire 1 * rst $end
$var wire 1 , parity_en $end
$var wire 1 - valid_in $end
$var reg 1 D load_en $end
$var reg 1 E shift_en $end
$var reg 1 F busy $end
$var reg 2 G sel [1:0] $end
$var reg 3 H current_state [2:0] $end
$var reg 3 I next_state [2:0] $end
$var reg 3 J count [2:0] $end
$upscope $end
$upscope $end
$upscope $end
$enddefinitions $end
#0
$dumpvars
0!
0"
0#
0$
0%
b0 &
bx <
0=
1>
0D
0E
0F
b11 G
b0 H
b0 I
b0 J
b0 ?
b1 @
b10 A
b11 B
b100 C
1'
0(
x6
07
08
09
1;
1:
05
04
03
02
01
00
0/
0.
0-
0,
0+
0*
0)
$end
#5000
1!
1)
#10000
0!
0)
#15000
1!
1)
#20000
1"
0!
1*
0)
b0 <
06
#25000
1!
1)
#30000
0!
0)
#35000
1!
1)
#40000
b10100101 &
1$
1%
0!
15
13
10
1.
1,
1-
0)
1F
0F
1D
b1 I
18
#45000
1!
1)
#50000
0%
0!
0-
0)
0D
1F
b0 I
0F
08
b1 H
1F
b1 I
b0 G
b10 I
1(
0;
0:
0>
0'
#55000
1!
1)
#60000
0!
0)
b10 H
b11 G
b1 G
1E
19
1;
#65000
1!
1)
#70000
0!
0)
b1 J
0E
b11 G
b1 G
1E
#75000
1!
1)
#80000
0!
0)
b10 J
0E
b11 G
b1 G
1E
#85000
1!
1)
#90000
0!
0)
b11 J
0E
b11 G
b1 G
1E
#95000
1!
1)
#100000
0!
0)
b100 J
0E
b11 G
b1 G
1E
#105000
1!
1)
#110000
0!
0)
b101 J
0E
b11 G
b1 G
1E
#115000
1!
1)
#120000
0!
0)
b110 J
0E
b11 G
b1 G
1E
#125000
1!
1)
#130000
0!
0)
b111 J
0E
b11 G
b1 G
1E
b11 I
#135000
1!
1)
#140000
0!
0)
b11 H
b0 J
0E
b11 G
b10 G
b100 I
09
0;
1:
#145000
1!
1)
#150000
0!
0)
b100 H
b11 G
b0 I
1;
1>
1'
#155000
1!
1)
#160000
0!
0)
b0 H
0F
0(
#165000
1!
1)
#170000
0!
0)
#175000
1!
1)
#180000
b111100 &
1#
1%
0!
05
12
11
0.
1+
1-
0)
1F
0F
1D
b1 I
1=
18
17
#185000
1!
1)
#190000
0%
0!
0-
0)
0D
1F
b0 I
0F
08
b1 H
1F
b1 I
b0 G
b10 I
1(
0;
0:
0>
0'
#195000
1!
1)
#200000
0!
0)
b10 H
b11 G
b1 G
1E
19
1;
#205000
1!
1)
#210000
0!
0)
b1 J
0E
b11 G
b1 G
1E
#215000
1!
1)
#220000
0!
0)
b10 J
0E
b11 G
b1 G
1E
#225000
1!
1)
#230000
0!
0)
b11 J
0E
b11 G
b1 G
1E
#235000
1!
1)
#240000
0!
0)
b100 J
0E
b11 G
b1 G
1E
#245000
1!
1)
#250000
0!
0)
b101 J
0E
b11 G
b1 G
1E
#255000
1!
1)
#260000
0!
0)
b110 J
0E
b11 G
b1 G
1E
#265000
1!
1)
#270000
0!
0)
b111 J
0E
b11 G
b1 G
1E
b11 I
#275000
1!
1)
#280000
0!
0)
b11 H
b0 J
0E
b11 G
b10 G
b100 I
09
0;
1:
1>
1'
#285000
1!
1)
#290000
0!
0)
b100 H
b11 G
b0 I
1;
#295000
1!
1)
#300000
0!
0)
b0 H
0F
0(
#305000
1!
1)
#310000
0!
0)
#315000
1!
1)
#320000
b11111111 &
0$
1%
0!
15
14
1/
1.
0,
1-
0)
1F
0F
1D
b1 I
0=
18
07
#325000
1!
1)
#330000
0%
0!
0-
0)
0D
1F
b0 I
0F
08
b1 H
1F
b1 I
b0 G
b10 I
1(
0;
0:
0>
0'
#335000
1!
1)
#340000
0!
0)
b10 H
b11 G
b1 G
1E
19
1;
#345000
1!
1)
#350000
0!
0)
b1 J
0E
b11 G
b1 G
1E
#355000
1!
1)
#360000
0!
0)
b10 J
0E
b11 G
b1 G
1E
#365000
1!
1)
#370000
0!
0)
b11 J
0E
b11 G
b1 G
1E
#375000
1!
1)
#380000
0!
0)
b100 J
0E
b11 G
b1 G
1E
#385000
1!
1)
#390000
0!
0)
b101 J
0E
b11 G
b1 G
1E
#395000
1!
1)
#400000
0!
0)
b110 J
0E
b11 G
b1 G
1E
#405000
1!
1)
#410000
0!
0)
b111 J
0E
b11 G
b1 G
1E
b100 I
#415000
1!
1)
#420000
0!
0)
b100 H
b0 J
0E
b11 G
b0 I
09
1:
1>
1'
#425000
1!
1)
#430000
0!
0)
b0 H
0F
0(
#435000
1!
1)
#440000
0!
0)
#445000
1!
1)
#450000
b1010101 &
1$
0#
1%
0!
04
02
00
0.
1,
0+
1-
0)
1F
0F
1D
b1 I
18
#455000
1!
1)
#460000
0%
0!
0-
0)
0D
1F
b0 I
0F
08
b1 H
1F
b1 I
b0 G
b10 I
1(
0;
0:
0>
0'
#465000
1!
1)
#470000
0!
0)
b10 H
b11 G
b1 G
1E
19
1;
#475000
1!
1)
#480000
0!
0)
b1 J
0E
b11 G
b1 G
1E
#485000
1!
1)
#490000
0!
0)
b10 J
0E
b11 G
b1 G
1E
#495000
1!
1)
#500000
0!
0)
b11 J
0E
b11 G
b1 G
1E
#505000
1!
1)
#510000
0!
0)
b100 J
0E
b11 G
b1 G
1E
#515000
1!
1)
#520000
0!
0)
b101 J
0E
b11 G
b1 G
1E
#525000
1!
1)
#530000
0!
0)
b110 J
0E
b11 G
b1 G
1E
#535000
1!
1)
#540000
0!
0)
b111 J
0E
b11 G
b1 G
1E
b11 I
#545000
1!
1)
#550000
0!
0)
b11 H
b0 J
0E
b11 G
b10 G
b100 I
09
0;
1:
#555000
1!
1)
#560000
0!
0)
b100 H
b11 G
b0 I
1;
1>
1'
#565000
1!
1)
#570000
0!
0)
b0 H
0F
0(
b11001100 &
1%
05
12
01
1.
1-
1F
0F
1D
b1 I
18
#575000
1!
1)
#580000
0%
0!
0-
0)
0D
1F
b0 I
0F
08
b1 H
1F
b1 I
b0 G
b10 I
1(
0;
0:
0>
0'
#585000
1!
1)
#590000
0!
0)
b10 H
b11 G
b1 G
1E
19
1;
#595000
1!
1)
#600000
0!
0)
b1 J
0E
b11 G
b1 G
1E
#605000
1!
1)
#610000
0!
0)
b10 J
0E
b11 G
b1 G
1E
#615000
1!
1)
#620000
0!
0)
b11 J
0E
b11 G
b1 G
1E
#625000
1!
1)
#630000
0!
0)
b100 J
0E
b11 G
b1 G
1E
#635000
1!
1)
#640000
0!
0)
b101 J
0E
b11 G
b1 G
1E
#645000
1!
1)
#650000
0!
0)
b110 J
0E
b11 G
b1 G
1E
#655000
1!
1)
#660000
0!
0)
b111 J
0E
b11 G
b1 G
1E
b11 I
#665000
1!
1)
#670000
0!
0)
b11 H
b0 J
0E
b11 G
b10 G
b100 I
09
0;
1:
#675000
1!
1)
#680000
0!
0)
b100 H
b11 G
b0 I
1;
1>
1'
#685000
1!
1)
#690000
0!
0)
b0 H
0F
0(
